flytekitplugins_onnxscikitlearn-1.16.12-py3.14-nspkg.pth
flytekitplugins/onnxscikitlearn/__init__.py
flytekitplugins/onnxscikitlearn/schema.py
flytekitplugins_onnxscikitlearn-1.16.12.dist-info/METADATA
flytekitplugins_onnxscikitlearn-1.16.12.dist-info/WHEEL
flytekitplugins_onnxscikitlearn-1.16.12.dist-info/namespace_packages.txt
flytekitplugins_onnxscikitlearn-1.16.12.dist-info/top_level.txt
flytekitplugins_onnxscikitlearn-1.16.12.dist-info/RECORD
