Metadata-Version: 2.4
Name: flytekitplugins-onnxscikitlearn
Version: 1.16.12
Summary: ONNX ScikitLearn Plugin for Flytekit
Author: flyteorg
Author-email: admin@flyte.org
License: apache2
Classifier: Intended Audience :: Science/Research
Classifier: Intended Audience :: Developers
Classifier: License :: OSI Approved :: Apache Software License
Classifier: Programming Language :: Python :: 3.9
Classifier: Programming Language :: Python :: 3.10
Classifier: Topic :: Scientific/Engineering
Classifier: Topic :: Scientific/Engineering :: Artificial Intelligence
Classifier: Topic :: Software Development
Classifier: Topic :: Software Development :: Libraries
Classifier: Topic :: Software Development :: Libraries :: Python Modules
Requires-Python: >=3.9
Requires-Dist: flytekit
Requires-Dist: skl2onnx<1.19.0,>=1.10.3
Requires-Dist: networkx<3.2; python_version < "3.9"
Requires-Dist: onnx<1.18.0
Dynamic: author
Dynamic: author-email
Dynamic: classifier
Dynamic: license
Dynamic: requires-dist
Dynamic: requires-python
Dynamic: summary
